{
  "gen": 40,
  "win_rate": 0.6875,
  "avg_hp": 11.1,
  "steps": 7708,
  "buffer_size": 47132,
  "episodes": 256,
  "encounter_set": "lean-decks-v1",
  "policy_loss": 0.49262,
  "value_loss": 0.03279,
  "adv_loss": 0.09652,
  "adv_pred_mag": 0.1958,
  "adv_target_mag": 0.1914,
  "num_sims": 1000,
  "gen_time": 676.48,
  "timestamp": 1776769406.9436972,
  "grad_cos_pv_mean": 0.0131,
  "grad_cos_pv_std": 0.0622,
  "grad_norm_p_mean": 0.1712,
  "grad_norm_v_mean": 0.3712,
  "grad_conflict_samples": 37,
  "kl_mcts_net_mean": -0.272,
  "top1_agree_mean": 0.8107,
  "value_corr_mean": 0.9495,
  "num_generations": 128,
  "best_win_rate": 0.7578,
  "phase": "SELFPLAY"
}